LICENSE
MANIFEST.in
README.rst
buildout.cfg
requirements.txt
setup.py
version.txt
bob/__init__.py
bob.db.drive.egg-info/PKG-INFO
bob.db.drive.egg-info/SOURCES.txt
bob.db.drive.egg-info/dependency_links.txt
bob.db.drive.egg-info/entry_points.txt
bob.db.drive.egg-info/not-zip-safe
bob.db.drive.egg-info/requires.txt
bob.db.drive.egg-info/top_level.txt
bob/db/__init__.py
bob/db/drive/__init__.py
bob/db/drive/checkfiles.py
bob/db/drive/create.py
bob/db/drive/drive_db_default.json
bob/db/drive/drive_test.csv
bob/db/drive/drive_train.csv
bob/db/drive/driver.py
bob/db/drive/models.py
bob/db/drive/query.py
bob/db/drive/test.py
doc/guide.rst
doc/index.rst
doc/links.rst
doc/py_api.rst
doc/img/bob-128x128.png
doc/img/bob-favicon.ico
doc/img/bob-logo.png